MANIFEST.in
README.rst
setup.py
django_track.egg-info/PKG-INFO
django_track.egg-info/SOURCES.txt
django_track.egg-info/dependency_links.txt
django_track.egg-info/requires.txt
django_track.egg-info/top_level.txt
tests/__init__.py
tests/integration/__init__.py
tests/unit/__init__.py
tests/unit/test_models.py
tests/unit/test_views.py
track/__init__.py
track/middleware.py
track/models.py
track/views.py
track/migrations/0001_create_visit.py
track/migrations/__init__.py
track/static/track/track.css
track/static/track/track.js
track/templates/track/analytics.html